parserllm/__init__.py
parserllm/parserllm.py
parserllm-0.0.2.dist-info/LICENSE
parserllm-0.0.2.dist-info/METADATA
parserllm-0.0.2.dist-info/WHEEL
parserllm-0.0.2.dist-info/RECORD
